Metadata-Version: 2.1
Name: swagger-marshmallow-codegen
Version: 0.6.5
Summary: "generating marshmallow's schema from swagger definition file"
Home-page: https://github.com/podhmo/swagger-marshmallow-codegen
Author: podhmo
Author-email: ababjam61+github@gmail.com
License: UNKNOWN
Keywords: swagger,codegen,marshmallow,code-generation,schema
Platform: UNKNOWN
Classifier: License :: OSI Approved :: MIT License
Classifier: Programming Language :: Python :: 3
Classifier: Development Status :: 4 - Beta
License-File: LICENSE
Requires-Dist: dictknife[load] (>=0.14.0)
Requires-Dist: magicalimport
Requires-Dist: marshmallow (>=3.0.0)
Requires-Dist: prestring
Requires-Dist: typing-extensions
Provides-Extra: dev
Requires-Dist: black ; extra == 'dev'
Requires-Dist: flake8 ; extra == 'dev'
Provides-Extra: docs
Provides-Extra: testing
Requires-Dist: pytest ; extra == 'testing'
